{
  "legislative_session": "2026R1",
  "identifier": "SB1580",
  "title": "Relating to compensation for journalism.",
  "from_organization": "~{\"classification\": \"upper\"}",
  "classification": [
    "bill"
  ],
  "subject": [],
  "abstracts": [
    {
      "note": "summary",
      "abstract": "Prohibits an online news aggregating platform from accessing for an Oregon audience the online content of a digital journalism provider without an agreement. Specifies requirements that an agreement must meet. Creates a private cause of action that a digital journalism provider may bring against a platform if the platform accesses for an Oregon audience the online content of the digital journalism provider without an agreement or fails to comply with an agreement. Allows for the recovery of the greater of statutory or actual damages, and for punitive damages. Bars a cause of action if the platform is participating in arbitration or in compliance with a final arbitration order, judgment or settlement agreement. Bars a cause of action for access that occurs between January 1, 2027, and December 31, 2028, if the platform elects to pay a certain sum amount. Allows a platform or group of digital journalism providers to initiate an arbitration process to determine a percentage of the platform's advertising revenue to be remitted to the digital journalism providers. Requires platforms to report annually certain information about compensation paid to digital journalism providers. Establishes the Oregon Civic Information Consortium. Directs the consortium to award grants for applicants that seek to improve civic information."
    }
  ],
  "other_titles": [],
  "other_identifiers": [
    {
      "identifier": "ocd-bill-or-2026r1-sb1580"
    }
  ],
  "actions": [
    {
      "description": "Introduction and first reading. Referred to President's desk.",
      "date": "2026-02-02T15:32:59+00:00",
      "organization_id": "~{\"classification\": \"upper\"}",
      "classification": [
        "introduction",
        "reading-1",
        "referral-committee"
      ],
      "related_entities": [],
      "_processing": {
        "log_file_created": "2026-07-15T13:24:31Z"
      }
    },
    {
      "description": "Referred to Commerce and General Government.",
      "date": "2026-02-02T17:38:57+00:00",
      "organization_id": "~{\"classification\": \"upper\"}",
      "classification": [
        "referral-committee"
      ],
      "related_entities": [],
      "_processing": {
        "log_file_created": "2026-07-15T13:24:31Z"
      }
    },
    {
      "description": "Public Hearing held.",
      "date": "2026-02-11T16:01:00+00:00",
      "organization_id": "~{\"classification\": \"upper\"}",
      "classification": [],
      "related_entities": [],
      "_processing": {
        "log_file_created": "2026-07-15T13:24:31Z"
      }
    },
    {
      "description": "In committee upon adjournment.",
      "date": "2026-03-07T00:17:00+00:00",
      "organization_id": "~{\"classification\": \"upper\"}",
      "classification": [],
      "related_entities": [],
      "_processing": {
        "log_file_created": "2026-07-15T13:24:31Z"
      }
    }
  ],
  "sponsorships": [
    {
      "name": "Khanh Pham",
      "classification": "primary",
      "entity_type": "person",
      "primary": true,
      "person_id": "~{\"name\": \"Khanh Pham\"}",
      "organization_id": null
    },
    {
      "name": "David Gomberg",
      "classification": "primary",
      "entity_type": "person",
      "primary": true,
      "person_id": "~{\"name\": \"David Gomberg\"}",
      "organization_id": null
    },
    {
      "name": "Sara Gelser Blouin",
      "classification": "primary",
      "entity_type": "person",
      "primary": true,
      "person_id": "~{\"name\": \"Sara Gelser Blouin\"}",
      "organization_id": null
    },
    {
      "name": "Lew Frederick",
      "classification": "cosponsor",
      "entity_type": "person",
      "primary": false,
      "person_id": "~{\"name\": \"Lew Frederick\"}",
      "organization_id": null
    },
    {
      "name": "Kayse Jama",
      "classification": "cosponsor",
      "entity_type": "person",
      "primary": false,
      "person_id": "~{\"name\": \"Kayse Jama\"}",
      "organization_id": null
    },
    {
      "name": "Courtney Neron Misslin",
      "classification": "cosponsor",
      "entity_type": "person",
      "primary": false,
      "person_id": "~{\"name\": \"Courtney Neron Misslin\"}",
      "organization_id": null
    },
    {
      "name": "Farrah Chaichi",
      "classification": "cosponsor",
      "entity_type": "person",
      "primary": false,
      "person_id": "~{\"name\": \"Farrah Chaichi\"}",
      "organization_id": null
    },
    {
      "name": "Willy Chotzen",
      "classification": "cosponsor",
      "entity_type": "person",
      "primary": false,
      "person_id": "~{\"name\": \"Willy Chotzen\"}",
      "organization_id": null
    },
    {
      "name": "Mark Gamba",
      "classification": "cosponsor",
      "entity_type": "person",
      "primary": false,
      "person_id": "~{\"name\": \"Mark Gamba\"}",
      "organization_id": null
    },
    {
      "name": "Darin Harbick",
      "classification": "cosponsor",
      "entity_type": "person",
      "primary": false,
      "person_id": "~{\"name\": \"Darin Harbick\"}",
      "organization_id": null
    },
    {
      "name": "Sarah McDonald",
      "classification": "cosponsor",
      "entity_type": "person",
      "primary": false,
      "person_id": "~{\"name\": \"Sarah McDonald \"}",
      "organization_id": null
    },
    {
      "name": "Lesly Mu\u00f1oz",
      "classification": "cosponsor",
      "entity_type": "person",
      "primary": false,
      "person_id": "~{\"name\": \"Lesly Mu\\u00f1oz\"}",
      "organization_id": null
    },
    {
      "name": "Lamar Wise",
      "classification": "cosponsor",
      "entity_type": "person",
      "primary": false,
      "person_id": "~{\"name\": \"Lamar Wise\"}",
      "organization_id": null
    },
    {
      "name": "James Manning Jr.",
      "classification": "primary",
      "entity_type": "person",
      "primary": true,
      "person_id": "~{\"name\": \"James Manning Jr.\"}",
      "organization_id": null
    },
    {
      "name": "Deb Patterson",
      "classification": "cosponsor",
      "entity_type": "person",
      "primary": false,
      "person_id": "~{\"name\": \"Deb Patterson\"}",
      "organization_id": null
    }
  ],
  "related_bills": [],
  "versions": [
    {
      "note": "Introduced",
      "links": [
        {
          "url": "https://olis.oregonlegislature.gov/liz/2026R1/Downloads/MeasureDocument/SB1580/Introduced",
          "media_type": "application/pdf"
        }
      ],
      "date": "",
      "classification": ""
    }
  ],
  "documents": [
    {
      "note": "2026-02-11 Proposed Amendment -2",
      "links": [
        {
          "url": "https://olis.oregonlegislature.gov/liz/2026R1/Downloads/ProposedAmendment/30271",
          "media_type": "application/pdf"
        }
      ],
      "date": "2026-02-11",
      "classification": ""
    }
  ],
  "citations": [],
  "sources": [
    {
      "url": "https://olis.oregonlegislature.gov/liz/2026R1/Measures/Overview/SB1580",
      "note": ""
    }
  ],
  "extras": {},
  "jurisdiction": {
    "id": "ocd-jurisdiction/country:us/state:or/government",
    "name": "Oregon",
    "classification": "state",
    "division_id": "ocd-division/country:us/state:or"
  },
  "_processing": {
    "logs_latest_update": "2026-07-15T13:24:31Z",
    "text_extraction_latest_update": "2026-07-21T06:39:57.615498Z"
  }
}