{
  "legislative_session": "2026R1",
  "identifier": "HB4162",
  "title": "Relating to cannabis worker unionization.",
  "from_organization": "~{\"classification\": \"lower\"}",
  "classification": [
    "bill"
  ],
  "subject": [],
  "abstracts": [
    {
      "note": "summary",
      "abstract": "Repeals Ballot Measure 119 (2024) that requires certain licensees of the Oregon Liquor and Cannabis Commission to enter into labor peace agreements with bona fide labor organizations representing the licensees' employees."
    }
  ],
  "other_titles": [],
  "other_identifiers": [
    {
      "identifier": "ocd-bill-or-2026r1-hb4162"
    }
  ],
  "actions": [
    {
      "description": "First reading. Referred to Speaker's desk.",
      "date": "2026-02-05T18:16:55+00:00",
      "organization_id": "~{\"classification\": \"lower\"}",
      "classification": [
        "introduction",
        "reading-1",
        "referral-committee"
      ],
      "related_entities": [],
      "_processing": {
        "log_file_created": "2026-07-15T13:24:31Z"
      }
    },
    {
      "description": "Referred to Rules.",
      "date": "2026-02-05T20:13:21+00:00",
      "organization_id": "~{\"classification\": \"lower\"}",
      "classification": [
        "referral-committee"
      ],
      "related_entities": [],
      "_processing": {
        "log_file_created": "2026-07-15T13:24:31Z"
      }
    },
    {
      "description": "Public Hearing held.",
      "date": "2026-02-10T16:01:00+00:00",
      "organization_id": "~{\"classification\": \"lower\"}",
      "classification": [],
      "related_entities": [],
      "_processing": {
        "log_file_created": "2026-07-15T13:24:31Z"
      }
    },
    {
      "description": "Work Session held.",
      "date": "2026-02-12T16:02:00+00:00",
      "organization_id": "~{\"classification\": \"lower\"}",
      "classification": [],
      "related_entities": [],
      "_processing": {
        "log_file_created": "2026-07-15T13:24:31Z"
      }
    },
    {
      "description": "Recommendation: Do pass.",
      "date": "2026-02-13T22:24:32+00:00",
      "organization_id": "~{\"classification\": \"lower\"}",
      "classification": [
        "committee-passage-favorable"
      ],
      "related_entities": [],
      "_processing": {
        "log_file_created": "2026-07-15T13:24:31Z"
      }
    },
    {
      "description": "Second reading.",
      "date": "2026-02-16T19:37:59+00:00",
      "organization_id": "~{\"classification\": \"lower\"}",
      "classification": [
        "reading-2"
      ],
      "related_entities": [],
      "_processing": {
        "log_file_created": "2026-07-15T13:24:31Z"
      }
    },
    {
      "description": "Third reading. Carried by Grayber. Passed.",
      "date": "2026-02-18T00:15:33+00:00",
      "organization_id": "~{\"classification\": \"lower\"}",
      "classification": [
        "passage",
        "reading-3"
      ],
      "related_entities": [],
      "_processing": {
        "log_file_created": "2026-07-15T13:24:31Z"
      }
    },
    {
      "description": "First reading. Referred to President's desk.",
      "date": "2026-02-19T22:10:27+00:00",
      "organization_id": "~{\"classification\": \"upper\"}",
      "classification": [
        "introduction",
        "reading-1",
        "referral-committee"
      ],
      "related_entities": [],
      "_processing": {
        "log_file_created": "2026-07-15T13:24:31Z"
      }
    },
    {
      "description": "Referred to Rules.",
      "date": "2026-02-19T23:17:20+00:00",
      "organization_id": "~{\"classification\": \"upper\"}",
      "classification": [
        "referral-committee"
      ],
      "related_entities": [],
      "_processing": {
        "log_file_created": "2026-07-15T13:24:31Z"
      }
    },
    {
      "description": "Public Hearing held.",
      "date": "2026-02-23T16:01:00+00:00",
      "organization_id": "~{\"classification\": \"upper\"}",
      "classification": [],
      "related_entities": [],
      "_processing": {
        "log_file_created": "2026-07-15T13:24:31Z"
      }
    },
    {
      "description": "Work Session held.",
      "date": "2026-02-25T16:02:00+00:00",
      "organization_id": "~{\"classification\": \"upper\"}",
      "classification": [],
      "related_entities": [],
      "_processing": {
        "log_file_created": "2026-07-15T13:24:31Z"
      }
    },
    {
      "description": "Recommendation: Do pass.",
      "date": "2026-02-26T16:41:45+00:00",
      "organization_id": "~{\"classification\": \"upper\"}",
      "classification": [
        "committee-passage-favorable"
      ],
      "related_entities": [],
      "_processing": {
        "log_file_created": "2026-07-15T13:24:31Z"
      }
    },
    {
      "description": "Second reading.",
      "date": "2026-02-26T18:28:49+00:00",
      "organization_id": "~{\"classification\": \"upper\"}",
      "classification": [
        "reading-2"
      ],
      "related_entities": [],
      "_processing": {
        "log_file_created": "2026-07-15T13:24:31Z"
      }
    },
    {
      "description": "Carried over to 03-02 by unanimous consent.",
      "date": "2026-02-27T20:49:42+00:00",
      "organization_id": "~{\"classification\": \"upper\"}",
      "classification": [],
      "related_entities": [],
      "_processing": {
        "log_file_created": "2026-07-15T13:24:31Z"
      }
    },
    {
      "description": "Third reading.  Carried by Jama.  Passed.",
      "date": "2026-03-02T21:38:45+00:00",
      "organization_id": "~{\"classification\": \"upper\"}",
      "classification": [
        "passage",
        "reading-3"
      ],
      "related_entities": [],
      "_processing": {
        "log_file_created": "2026-07-15T13:24:31Z"
      }
    },
    {
      "description": "Speaker signed.",
      "date": "2026-03-04T17:42:52+00:00",
      "organization_id": "~{\"classification\": \"lower\"}",
      "classification": [
        "passage"
      ],
      "related_entities": [],
      "_processing": {
        "log_file_created": "2026-07-15T13:24:31Z"
      }
    },
    {
      "description": "President signed.",
      "date": "2026-03-05T16:38:22+00:00",
      "organization_id": "~{\"classification\": \"upper\"}",
      "classification": [
        "passage"
      ],
      "related_entities": [],
      "_processing": {
        "log_file_created": "2026-07-15T13:24:31Z"
      }
    },
    {
      "description": "Governor signed.",
      "date": "2026-03-31T21:07:00+00:00",
      "organization_id": "~{\"classification\": \"lower\"}",
      "classification": [
        "executive-signature"
      ],
      "related_entities": [],
      "_processing": {
        "log_file_created": "2026-07-15T13:24:31Z"
      }
    },
    {
      "description": "Chapter 73, (2026 Laws): Effective date January 1, 2027.",
      "date": "2026-04-06T17:33:05+00:00",
      "organization_id": "~{\"classification\": \"lower\"}",
      "classification": [],
      "related_entities": [],
      "_processing": {
        "log_file_created": "2026-07-15T13:24:31Z"
      }
    }
  ],
  "sponsorships": [],
  "related_bills": [],
  "versions": [
    {
      "note": "Enrolled",
      "links": [
        {
          "url": "https://olis.oregonlegislature.gov/liz/2026R1/Downloads/MeasureDocument/HB4162/Enrolled",
          "media_type": "application/pdf"
        }
      ],
      "date": "",
      "classification": ""
    },
    {
      "note": "Introduced",
      "links": [
        {
          "url": "https://olis.oregonlegislature.gov/liz/2026R1/Downloads/MeasureDocument/HB4162/Introduced",
          "media_type": "application/pdf"
        }
      ],
      "date": "",
      "classification": ""
    }
  ],
  "documents": [],
  "citations": [],
  "sources": [
    {
      "url": "https://olis.oregonlegislature.gov/liz/2026R1/Measures/Overview/HB4162",
      "note": ""
    }
  ],
  "extras": {},
  "jurisdiction": {
    "id": "ocd-jurisdiction/country:us/state:or/government",
    "name": "Oregon",
    "classification": "state",
    "division_id": "ocd-division/country:us/state:or"
  },
  "_processing": {
    "logs_latest_update": "2026-07-15T13:24:31Z"
  }
}